{"bol+achacachi":{"en":{"value":"Achacachi","trigram":["achacachi","ach","cha","hac","aca","cac","chi","acha","chac","haca","acac","cach","achi","achac","chaca","hacac","acach","cachi"]}},"bol+bermejo":{"en":{"value":"Bermejo","trigram":["bermejo","ber","erm","rme","mej","ejo","berm","erme","rmej","mejo","berme","ermej","rmejo"]}},"bol+ascension":{"en":{"value":"Ascension","trigram":["ascension","asc","sce","cen","ens","nsi","sio","ion","asce","scen","cens","ensi","nsio","sion","ascen","scens","censi","ensio","nsion"]}},"bol+baures":{"en":{"value":"Baures","trigram":["baures","bau","aur","ure","res","baur","aure","ures","baure","aures"]}},"bol+apolo":{"en":{"value":"Apolo","trigram":["apolo","apo","pol","olo","apol","polo"]}},"bol+aiquile":{"en":{"value":"Aiquile","trigram":["aiquile","aiq","iqu","qui","uil","ile","aiqu","iqui","quil","uile","aiqui","iquil","quile"]}},"bol+cobija":{"en":{"value":"Cobija","trigram":["cobija","cob","obi","bij","ija","cobi","obij","bija","cobij","obija"]}},"bol+chulumani":{"en":{"value":"Chulumani","trigram":["chulumani","chu","hul","ulu","lum","uma","man","ani","chul","hulu","ulum","luma","uman","mani","chulu","hulum","uluma","luman","umani"]}},"bol+cliza":{"en":{"value":"Cliza","trigram":["cliza","cli","liz","iza","cliz","liza"]}},"bol+betanzos":{"en":{"value":"Betanzos","trigram":["betanzos","bet","eta","tan","anz","nzo","zos","beta","etan","tanz","anzo","nzos","betan","etanz","tanzo","anzos"]}},"bol+charana":{"en":{"value":"Charana","trigram":["charana","cha","har","ara","ran","ana","char","hara","aran","rana","chara","haran","arana"]}},"bol+charagua":{"en":{"value":"Charagua","trigram":["charagua","cha","har","ara","rag","agu","gua","char","hara","arag","ragu","agua","chara","harag","aragu","ragua"]}},"bol+camargo":{"en":{"value":"Camargo","trigram":["camargo","cam","ama","mar","arg","rgo","cama","amar","marg","argo","camar","amarg","margo"]}},"bol+challapata":{"en":{"value":"Challapata","trigram":["challapata","cha","hal","all","lla","lap","apa","pat","ata","chal","hall","alla","llap","lapa","apat","pata","chall","halla","allap","llapa","lapat","apata"]}},"bol+camiri":{"en":{"value":"Camiri","trigram":["camiri","cam","ami","mir","iri","cami","amir","miri","camir","amiri"]}},"bol+entre_rios":{"en":{"value":"Entre Rios","trigram":["entre","rios","ent","ntr","tre","re ","e r"," ri","rio","ios","entr","ntre","tre ","re r","e ri"," rio","ntre ","tre r","re ri","e rio"," rios"]}},"bol+coroico":{"en":{"value":"Coroico","trigram":["coroico","cor","oro","roi","oic","ico","coro","oroi","roic","oico","coroi","oroic","roico"]}},"bol+cuevo":{"en":{"value":"Cuevo","trigram":["cuevo","cue","uev","evo","cuev","uevo"]}},"bol+guayaramerin":{"en":{"value":"Guayaramerin","trigram":["guayaramerin","gua","uay","aya","yar","ara","ram","ame","mer","eri","rin","guay","uaya","ayar","yara","aram","rame","amer","meri","erin","guaya","uayar","ayara","yaram","arame","ramer","ameri","merin"]}},"bol+corocoro":{"en":{"value":"Corocoro","trigram":["corocoro","cor","oro","roc","oco","coro","oroc","roco","ocor","coroc","oroco","rocor","ocoro"]}},"bol+cochabamba":{"en":{"value":"Cochabamba","trigram":["cochabamba","coc","och","cha","hab","aba","bam","amb","mba","coch","ocha","chab","haba","abam","bamb","amba","cocha","ochab","chaba","habam","abamb","bamba"]}},"bol+comarapa":{"en":{"value":"Comarapa","trigram":["comarapa","com","oma","mar","ara","rap","apa","coma","omar","mara","arap","rapa","comar","omara","marap","arapa"]}},"bol+llallagua":{"en":{"value":"Llallagua","trigram":["llallagua","lla","lal","all","lag","agu","gua","llal","lall","alla","llag","lagu","agua","llall","lalla","allag","llagu","lagua"]}},"bol+la_paz":{"en":{"value":"La Paz","trigram":["la","paz","la ","a p"," pa","la p","a pa"," paz","la pa","a paz"]}},"bol+llica":{"en":{"value":"Llica","trigram":["llica","lli","lic","ica","llic","lica"]}},"bol+magdalena":{"en":{"value":"Magdalena","trigram":["magdalena","mag","agd","gda","dal","ale","len","ena","magd","agda","gdal","dale","alen","lena","magda","agdal","gdale","dalen","alena"]}},"bol+mapiri":{"en":{"value":"Mapiri","trigram":["mapiri","map","api","pir","iri","mapi","apir","piri","mapir","apiri"]}},"bol+montero":{"en":{"value":"Montero","trigram":["montero","mon","ont","nte","ter","ero","mont","onte","nter","tero","monte","onter","ntero"]}},"bol+portachuelo":{"en":{"value":"Portachuelo","trigram":["portachuelo","por","ort","rta","tac","ach","chu","hue","uel","elo","port","orta","rtac","tach","achu","chue","huel","uelo","porta","ortac","rtach","tachu","achue","chuel","huelo"]}},"bol+puerto_heath":{"en":{"value":"Puerto Heath","trigram":["puerto","heath","pue","uer","ert","rto","to ","o h"," he","hea","eat","ath","puer","uert","erto","rto ","to h","o he"," hea","heat","eath","puert","uerto","erto ","rto h","to he","o hea"," heat"]}},"bol+piso_firme":{"en":{"value":"Piso Firme","trigram":["piso","firme","pis","iso","so ","o f"," fi","fir","irm","rme","iso ","so f","o fi"," fir","firm","irme","piso ","iso f","so fi","o fir"," firm"]}},"bol+patacamaya":{"en":{"value":"Patacamaya","trigram":["patacamaya","pat","ata","tac","aca","cam","ama","may","aya","pata","atac","taca","acam","cama","amay","maya","patac","ataca","tacam","acama","camay","amaya"]}},"bol+potosi":{"en":{"value":"Potosi","trigram":["potosi","pot","oto","tos","osi","poto","otos","tosi","potos","otosi"]}},"bol+oruro":{"en":{"value":"Oruro","trigram":["oruro","oru","rur","uro","orur","ruro"]}},"bol+padilla":{"en":{"value":"Padilla","trigram":["padilla","pad","adi","dil","ill","lla","padi","adil","dill","illa","padil","adill","dilla"]}},"bol+puerto_acosta":{"en":{"value":"Puerto Acosta","trigram":["puerto","acosta","pue","uer","ert","rto","to ","o a"," ac","aco","cos","ost","sta","puer","uert","erto","rto ","to a","o ac"," aco","acos","cost","osta","puert","uerto","erto ","rto a","to ac","o aco"," acos","acost","costa"]}},"bol+puerto_quijarro":{"en":{"value":"Puerto Quijarro","trigram":["puerto","quijarro","pue","uer","ert","rto","to ","o q"," qu","qui","uij","ija","jar","arr","rro","puer","uert","erto","rto ","to q","o qu"," qui","quij","uija","ijar","jarr","arro","puert","uerto","erto ","rto q","to qu","o qui"," quij","quija","uijar","ijarr","jarro"]}},"bol+puerto_suarez":{"en":{"value":"Puerto Suarez","trigram":["puerto","suarez","pue","uer","ert","rto","to ","o s"," su","sua","uar","are","rez","puer","uert","erto","rto ","to s","o su"," sua","suar","uare","arez","puert","uerto","erto ","rto s","to su","o sua"," suar","suare","uarez"]}},"bol+puerto_villarroel":{"en":{"value":"Puerto Villarroel","trigram":["puerto","villarroel","pue","uer","ert","rto","to ","o v"," vi","vil","ill","lla","lar","arr","rro","roe","oel","puer","uert","erto","rto ","to v","o vi"," vil","vill","illa","llar","larr","arro","rroe","roel","puert","uerto","erto ","rto v","to vi","o vil"," vill","villa","illar","llarr","larro","arroe","rroel"]}},"bol+punata":{"en":{"value":"Punata","trigram":["punata","pun","una","nat","ata","puna","unat","nata","punat","unata"]}},"bol+quillacollo":{"en":{"value":"Quillacollo","trigram":["quillacollo","qui","uil","ill","lla","lac","aco","col","oll","llo","quil","uill","illa","llac","laco","acol","coll","ollo","quill","uilla","illac","llaco","lacol","acoll","collo"]}},"bol+quime":{"en":{"value":"Quime","trigram":["quime","qui","uim","ime","quim","uime"]}},"bol+reyes":{"en":{"value":"Reyes","trigram":["reyes","rey","eye","yes","reye","eyes"]}},"bol+sacaba":{"en":{"value":"Sacaba","trigram":["sacaba","sac","aca","cab","aba","saca","acab","caba","sacab","acaba"]}},"bol+sabaya":{"en":{"value":"Sabaya","trigram":["sabaya","sab","aba","bay","aya","saba","abay","baya","sabay","abaya"]}},"bol+rurrenabaque":{"en":{"value":"Rurrenabaque","trigram":["rurrenabaque","rur","urr","rre","ren","ena","nab","aba","baq","aqu","que","rurr","urre","rren","rena","enab","naba","abaq","baqu","aque","rurre","urren","rrena","renab","enaba","nabaq","abaqu","baque"]}},"bol+samaipata":{"en":{"value":"Samaipata","trigram":["samaipata","sam","ama","mai","aip","ipa","pat","ata","sama","amai","maip","aipa","ipat","pata","samai","amaip","maipa","aipat","ipata"]}},"bol+san_borja":{"en":{"value":"San Borja","trigram":["san","borja","an ","n b"," bo","bor","orj","rja","san ","an b","n bo"," bor","borj","orja","san b","an bo","n bor"," borj"]}},"bol+san_carlos":{"en":{"value":"San Carlos","trigram":["san","carlos","an ","n c"," ca","car","arl","rlo","los","san ","an c","n ca"," car","carl","arlo","rlos","san c","an ca","n car"," carl","carlo","arlos"]}},"bol+riberalta":{"en":{"value":"Riberalta","trigram":["riberalta","rib","ibe","ber","era","ral","alt","lta","ribe","iber","bera","eral","ralt","alta","riber","ibera","beral","eralt","ralta"]}},"bol+san_ignacio_de_velasco":{"en":{"value":"San Ignacio de Velasco","trigram":["san","ignacio","de","velasco","an ","n i"," ig","ign","gna","nac","aci","cio","io ","o d"," de","de ","e v"," ve","vel","ela","las","asc","sco","san ","an i","n ig"," ign","igna","gnac","naci","acio","cio ","io d","o de"," de ","de v","e ve"," vel","vela","elas","lasc","asco","san i","an ig","n ign"," igna","ignac","gnaci","nacio","acio ","cio d","io de","o de "," de v","de ve","e vel"," vela","velas","elasc","lasco"]}},"bol+san_javier":{"en":{"value":"San Javier","trigram":["san","javier","an ","n j"," ja","jav","avi","vie","ier","san ","an j","n ja"," jav","javi","avie","vier","san j","an ja","n jav"," javi","javie","avier"]}},"bol+robore":{"en":{"value":"Robore","trigram":["robore","rob","obo","bor","ore","robo","obor","bore","robor","obore"]}},"bol+san_jose_de_chiquitos":{"en":{"value":"San Jose de Chiquitos","trigram":["san","jose","de","chiquitos","an ","n j"," jo","jos","ose","se ","e d"," de","de ","e c"," ch","chi","hiq","iqu","qui","uit","ito","tos","san ","an j","n jo"," jos","ose ","se d","e de"," de ","de c","e ch"," chi","chiq","hiqu","iqui","quit","uito","itos","san j","an jo","n jos"," jose","jose ","ose d","se de","e de "," de c","de ch","e chi"," chiq","chiqu","hiqui","iquit","quito","uitos"]}},"bol+san_lorenzo":{"en":{"value":"San Lorenzo","trigram":["san","lorenzo","an ","n l"," lo","lor","ore","ren","enz","nzo","san ","an l","n lo"," lor","lore","oren","renz","enzo","san l","an lo","n lor"," lore","loren","orenz","renzo"]}},"bol+sicasica":{"en":{"value":"Sicasica","trigram":["sicasica","sic","ica","cas","asi","sica","icas","casi","asic","sicas","icasi","casic","asica"]}},"bol+sucre":{"en":{"value":"Sucre","trigram":["sucre","suc","ucr","cre","sucr","ucre"]}},"bol+sorata":{"en":{"value":"Sorata","trigram":["sorata","sor","ora","rat","ata","sora","orat","rata","sorat","orata"]}},"bol+santa_cruz":{"en":{"value":"Santa Cruz","trigram":["santa","cruz","san","ant","nta","ta ","a c"," cr","cru","ruz","sant","anta","nta ","ta c","a cr"," cru","anta ","nta c","ta cr","a cru"," cruz"]}},"bol+santa_ana_de_yacuma":{"en":{"value":"Santa Ana de Yacuma","trigram":["santa","ana","de","yacuma","san","ant","nta","ta ","a a"," an","na ","a d"," de","de ","e y"," ya","yac","acu","cum","uma","sant","anta","nta ","ta a","a an"," ana","ana ","na d","a de"," de ","de y","e ya"," yac","yacu","acum","cuma","anta ","nta a","ta an","a ana"," ana ","ana d","na de","a de "," de y","de ya","e yac"," yacu","yacum","acuma"]}},"bol+san_rafael":{"en":{"value":"San Rafael","trigram":["san","rafael","an ","n r"," ra","raf","afa","fae","ael","san ","an r","n ra"," raf","rafa","afae","fael","san r","an ra","n raf"," rafa","rafae","afael"]}},"bol+san_ramon":{"en":{"value":"San Ramon","trigram":["san","ramon","an ","n r"," ra","ram","amo","mon","san ","an r","n ra"," ram","ramo","amon","san r","an ra","n ram"," ramo"]}},"bol+san_matias":{"en":{"value":"San Matias","trigram":["san","matias","an ","n m"," ma","mat","ati","tia","ias","san ","an m","n ma"," mat","mati","atia","tias","san m","an ma","n mat"," mati","matia","atias"]}},"bol+tarabuco":{"en":{"value":"Tarabuco","trigram":["tarabuco","tar","ara","rab","abu","buc","uco","tara","arab","rabu","abuc","buco","tarab","arabu","rabuc","abuco"]}},"bol+uncia":{"en":{"value":"Uncia","trigram":["uncia","unc","nci","cia","unci","ncia"]}},"bol+vallegrande":{"en":{"value":"Vallegrande","trigram":["vallegrande","val","all","lle","leg","egr","gra","ran","and","nde","vall","alle","lleg","legr","egra","gran","rand","ande","valle","alleg","llegr","legra","egran","grand","rande"]}},"bol+villa_martin_colchak":{"en":{"value":"Villa Martin Colchak","trigram":["villa","martin","colchak","vil","ill","lla","la ","a m"," ma","mar","art","rti","tin","in ","n c"," co","col","olc","lch","cha","hak","vill","illa","lla ","la m","a ma"," mar","mart","arti","rtin","tin ","in c","n co"," col","colc","olch","lcha","chak","illa ","lla m","la ma","a mar"," mart","marti","artin","rtin ","tin c","in co","n col"," colc","colch","olcha","lchak"]}},"bol+uyuni":{"en":{"value":"Uyuni","trigram":["uyuni","uyu","yun","uni","uyun","yuni"]}},"bol+viacha":{"en":{"value":"Viacha","trigram":["viacha","via","iac","ach","cha","viac","iach","acha","viach","iacha"]}},"bol+tupiza":{"en":{"value":"Tupiza","trigram":["tupiza","tup","upi","piz","iza","tupi","upiz","piza","tupiz","upiza"]}},"bol+tarija":{"en":{"value":"Tarija","trigram":["tarija","tar","ari","rij","ija","tari","arij","rija","tarij","arija"]}},"bol+trinidad":{"en":{"value":"Trinidad","trigram":["trinidad","tri","rin","ini","nid","ida","dad","trin","rini","inid","nida","idad","trini","rinid","inida","nidad"]}},"bol+tiquipaya":{"en":{"value":"Tiquipaya","trigram":["tiquipaya","tiq","iqu","qui","uip","ipa","pay","aya","tiqu","iqui","quip","uipa","ipay","paya","tiqui","iquip","quipa","uipay","ipaya"]}},"bol+villa_tunari":{"en":{"value":"Villa Tunari","trigram":["villa","tunari","vil","ill","lla","la ","a t"," tu","tun","una","nar","ari","vill","illa","lla ","la t","a tu"," tun","tuna","unar","nari","illa ","lla t","la tu","a tun"," tuna","tunar","unari"]}},"bol+villazon":{"en":{"value":"Villazon","trigram":["villazon","vil","ill","lla","laz","azo","zon","vill","illa","llaz","lazo","azon","villa","illaz","llazo","lazon"]}},"bol+villamontes":{"en":{"value":"Villamontes","trigram":["villamontes","vil","ill","lla","lam","amo","mon","ont","nte","tes","vill","illa","llam","lamo","amon","mont","onte","ntes","villa","illam","llamo","lamon","amont","monte","ontes"]}},"bol+villa_yapacani":{"en":{"value":"Villa Yapacani","trigram":["villa","yapacani","vil","ill","lla","la ","a y"," ya","yap","apa","pac","aca","can","ani","vill","illa","lla ","la y","a ya"," yap","yapa","apac","paca","acan","cani","illa ","lla y","la ya","a yap"," yapa","yapac","apaca","pacan","acani"]}},"bol+yacuiba":{"en":{"value":"Yacuiba","trigram":["yacuiba","yac","acu","cui","uib","iba","yacu","acui","cuib","uiba","yacui","acuib","cuiba"]}},"bol+warnes":{"en":{"value":"Warnes","trigram":["warnes","war","arn","rne","nes","warn","arne","rnes","warne","arnes"]}},"bol+vinto":{"en":{"value":"Vinto","trigram":["vinto","vin","int","nto","vint","into"]}}}