{"ita+amelia":{"en":{"value":"Amelia","trigram":["amelia","ame","mel","eli","lia","amel","meli","elia","ameli","melia"]}},"ita+agrigento":{"en":{"value":"Agrigento","trigram":["agrigento","agr","gri","rig","ige","gen","ent","nto","agri","grig","rige","igen","gent","ento","agrig","grige","rigen","igent","gento"]}},"ita+ancona":{"en":{"value":"Ancona","trigram":["ancona","anc","nco","con","ona","anco","ncon","cona","ancon","ncona"]}},"ita+andria":{"en":{"value":"Andria","trigram":["andria","and","ndr","dri","ria","andr","ndri","dria","andri","ndria"]}},"ita+aosta":{"en":{"value":"Aosta","trigram":["aosta","aos","ost","sta","aost","osta"]}},"ita+arezzo":{"en":{"value":"Arezzo","trigram":["arezzo","are","rez","ezz","zzo","arez","rezz","ezzo","arezz","rezzo"]}},"ita+asti":{"en":{"value":"Asti","trigram":["asti","ast","sti"]}},"ita+avigliano":{"en":{"value":"Avigliano","trigram":["avigliano","avi","vig","igl","gli","lia","ian","ano","avig","vigl","igli","glia","lian","iano","avigl","vigli","iglia","glian","liano"]}},"ita+bari":{"en":{"value":"Bari","trigram":["bari","bar","ari"]}},"ita+bergamo":{"en":{"value":"Bergamo","trigram":["bergamo","ber","erg","rga","gam","amo","berg","erga","rgam","gamo","berga","ergam","rgamo"]}},"ita+barletta":{"en":{"value":"Barletta","trigram":["barletta","bar","arl","rle","let","ett","tta","barl","arle","rlet","lett","etta","barle","arlet","rlett","letta"]}},"ita+benevento":{"en":{"value":"Benevento","trigram":["benevento","ben","ene","nev","eve","ven","ent","nto","bene","enev","neve","even","vent","ento","benev","eneve","neven","event","vento"]}},"ita+brindisi":{"en":{"value":"Brindisi","trigram":["brindisi","bri","rin","ind","ndi","dis","isi","brin","rind","indi","ndis","disi","brind","rindi","indis","ndisi"]}},"ita+bolzano":{"en":{"value":"Bolzano","trigram":["bolzano","bol","olz","lza","zan","ano","bolz","olza","lzan","zano","bolza","olzan","lzano"]}},"ita+bologna":{"en":{"value":"Bologna","trigram":["bologna","bol","olo","log","ogn","gna","bolo","olog","logn","ogna","bolog","ologn","logna"]}},"ita+biella":{"en":{"value":"Biella","trigram":["biella","bie","iel","ell","lla","biel","iell","ella","biell","iella"]}},"ita+brescia":{"en":{"value":"Brescia","trigram":["brescia","bre","res","esc","sci","cia","bres","resc","esci","scia","bresc","resci","escia"]}},"ita+busto_arsizio":{"en":{"value":"Busto Arsizio","trigram":["busto","arsizio","bus","ust","sto","to ","o a"," ar","ars","rsi","siz","izi","zio","bust","usto","sto ","to a","o ar"," ars","arsi","rsiz","sizi","izio","usto ","sto a","to ar","o ars"," arsi","arsiz","rsizi","sizio"]}},"ita+cagliari":{"en":{"value":"Cagliari","trigram":["cagliari","cag","agl","gli","lia","iar","ari","cagl","agli","glia","liar","iari","cagli","aglia","gliar","liari"]}},"ita+campobasso":{"en":{"value":"Campobasso","trigram":["campobasso","cam","amp","mpo","pob","oba","bas","ass","sso","camp","ampo","mpob","poba","obas","bass","asso","campo","ampob","mpoba","pobas","obass","basso"]}},"ita+civitavecchia":{"en":{"value":"Civitavecchia","trigram":["civitavecchia","civ","ivi","vit","ita","tav","ave","vec","ecc","cch","chi","hia","civi","ivit","vita","itav","tave","avec","vecc","ecch","cchi","chia","civit","ivita","vitav","itave","tavec","avecc","vecch","ecchi","cchia"]}},"ita+como":{"en":{"value":"Como","trigram":["como","com","omo"]}},"ita+catanzaro":{"en":{"value":"Catanzaro","trigram":["catanzaro","cat","ata","tan","anz","nza","zar","aro","cata","atan","tanz","anza","nzar","zaro","catan","atanz","tanza","anzar","nzaro"]}},"ita+caserta":{"en":{"value":"Caserta","trigram":["caserta","cas","ase","ser","ert","rta","case","aser","sert","erta","caser","asert","serta"]}},"ita+catania":{"en":{"value":"Catania","trigram":["catania","cat","ata","tan","ani","nia","cata","atan","tani","ania","catan","atani","tania"]}},"ita+castellammare_di_stabia":{"en":{"value":"Castellammare di Stabia","trigram":["castellammare","di","stabia","cas","ast","ste","tel","ell","lla","lam","amm","mma","mar","are","re ","e d"," di","di ","i s"," st","sta","tab","abi","bia","cast","aste","stel","tell","ella","llam","lamm","amma","mmar","mare","are ","re d","e di"," di ","di s","i st"," sta","stab","tabi","abia","caste","astel","stell","tella","ellam","llamm","lamma","ammar","mmare","mare ","are d","re di","e di "," di s","di st","i sta"," stab","stabi","tabia"]}},"ita+eraclea":{"en":{"value":"Eraclea","trigram":["eraclea","era","rac","acl","cle","lea","erac","racl","acle","clea","eracl","racle","aclea"]}},"ita+forli":{"en":{"value":"Forli","trigram":["forli","for","orl","rli","forl","orli"]}},"ita+genoa":{"en":{"value":"Genoa","trigram":["genoa","gen","eno","noa","geno","enoa"]}},"ita+florence":{"en":{"value":"Florence","trigram":["florence","flo","lor","ore","ren","enc","nce","flor","lore","oren","renc","ence","flore","loren","orenc","rence"]}},"ita+crotone":{"en":{"value":"Crotone","trigram":["crotone","cro","rot","oto","ton","one","crot","roto","oton","tone","croto","roton","otone"]}},"ita+ferrara":{"en":{"value":"Ferrara","trigram":["ferrara","fer","err","rra","rar","ara","ferr","erra","rrar","rara","ferra","errar","rrara"]}},"ita+foggia":{"en":{"value":"Foggia","trigram":["foggia","fog","ogg","ggi","gia","fogg","oggi","ggia","foggi","oggia"]}},"ita+latina":{"en":{"value":"Latina","trigram":["latina","lat","ati","tin","ina","lati","atin","tina","latin","atina"]}},"ita+laquila":{"en":{"value":"L'Aquila","trigram":["l'aquila","l'a","'aq","aqu","qui","uil","ila","l'aq","'aqu","aqui","quil","uila","l'aqu","'aqui","aquil","quila"]}},"ita+gorizia":{"en":{"value":"Gorizia","trigram":["gorizia","gor","ori","riz","izi","zia","gori","oriz","rizi","izia","goriz","orizi","rizia"]}},"ita+messina":{"en":{"value":"Messina","trigram":["messina","mes","ess","ssi","sin","ina","mess","essi","ssin","sina","messi","essin","ssina"]}},"ita+loreto":{"en":{"value":"Loreto","trigram":["loreto","lor","ore","ret","eto","lore","oret","reto","loret","oreto"]}},"ita+macerata":{"en":{"value":"Macerata","trigram":["macerata","mac","ace","cer","era","rat","ata","mace","acer","cera","erat","rata","macer","acera","cerat","erata"]}},"ita+lecce":{"en":{"value":"Lecce","trigram":["lecce","lec","ecc","cce","lecc","ecce"]}},"ita+marsala":{"en":{"value":"Marsala","trigram":["marsala","mar","ars","rsa","sal","ala","mars","arsa","rsal","sala","marsa","arsal","rsala"]}},"ita+milan":{"en":{"value":"Milan","trigram":["milan","mil","ila","lan","mila","ilan"]}},"ita+giugliano_in_campania":{"en":{"value":"Giugliano in Campania","trigram":["giugliano","in","campania","giu","iug","ugl","gli","lia","ian","ano","no ","o i"," in","in ","n c"," ca","cam","amp","mpa","pan","ani","nia","giug","iugl","ugli","glia","lian","iano","ano ","no i","o in"," in ","in c","n ca"," cam","camp","ampa","mpan","pani","ania","giugl","iugli","uglia","glian","liano","iano ","ano i","no in","o in "," in c","in ca","n cam"," camp","campa","ampan","mpani","pania"]}},"ita+livorno":{"en":{"value":"Livorno","trigram":["livorno","liv","ivo","vor","orn","rno","livo","ivor","vorn","orno","livor","ivorn","vorno"]}},"ita+monza":{"en":{"value":"Monza","trigram":["monza","mon","onz","nza","monz","onza"]}},"ita+narni":{"en":{"value":"Narni","trigram":["narni","nar","arn","rni","narn","arni"]}},"ita+molfetta":{"en":{"value":"Molfetta","trigram":["molfetta","mol","olf","lfe","fet","ett","tta","molf","olfe","lfet","fett","etta","molfe","olfet","lfett","fetta"]}},"ita+montecastrilli":{"en":{"value":"Montecastrilli","trigram":["montecastrilli","mon","ont","nte","tec","eca","cas","ast","str","tri","ril","ill","lli","mont","onte","ntec","teca","ecas","cast","astr","stri","tril","rill","illi","monte","ontec","nteca","tecas","ecast","castr","astri","stril","trill","rilli"]}},"ita+naples":{"en":{"value":"Naples","trigram":["naples","nap","apl","ple","les","napl","aple","ples","naple","aples"]}},"ita+modena":{"en":{"value":"Modena","trigram":["modena","mod","ode","den","ena","mode","oden","dena","moden","odena"]}},"ita+muggia":{"en":{"value":"Muggia","trigram":["muggia","mug","ugg","ggi","gia","mugg","uggi","ggia","muggi","uggia"]}},"ita+novara":{"en":{"value":"Novara","trigram":["novara","nov","ova","var","ara","nova","ovar","vara","novar","ovara"]}},"ita+olbia":{"en":{"value":"Olbia","trigram":["olbia","olb","lbi","bia","olbi","lbia"]}},"ita+padova":{"en":{"value":"Padova","trigram":["padova","pad","ado","dov","ova","pado","adov","dova","padov","adova"]}},"ita+palermo":{"en":{"value":"Palermo","trigram":["palermo","pal","ale","ler","erm","rmo","pale","aler","lerm","ermo","paler","alerm","lermo"]}},"ita+parma":{"en":{"value":"Parma","trigram":["parma","par","arm","rma","parm","arma"]}},"ita+perugia":{"en":{"value":"Perugia","trigram":["perugia","per","eru","rug","ugi","gia","peru","erug","rugi","ugia","perug","erugi","rugia"]}},"ita+piacenza":{"en":{"value":"Piacenza","trigram":["piacenza","pia","iac","ace","cen","enz","nza","piac","iace","acen","cenz","enza","piace","iacen","acenz","cenza"]}},"ita+pescara":{"en":{"value":"Pescara","trigram":["pescara","pes","esc","sca","car","ara","pesc","esca","scar","cara","pesca","escar","scara"]}},"ita+pozzallo":{"en":{"value":"Pozzallo","trigram":["pozzallo","poz","ozz","zza","zal","all","llo","pozz","ozza","zzal","zall","allo","pozza","ozzal","zzall","zallo"]}},"ita+potenza":{"en":{"value":"Potenza","trigram":["potenza","pot","ote","ten","enz","nza","pote","oten","tenz","enza","poten","otenz","tenza"]}},"ita+pisa":{"en":{"value":"Pisa","trigram":["pisa","pis","isa"]}},"ita+priverno":{"en":{"value":"Priverno","trigram":["priverno","pri","riv","ive","ver","ern","rno","priv","rive","iver","vern","erno","prive","river","ivern","verno"]}},"ita+prato":{"en":{"value":"Prato","trigram":["prato","pra","rat","ato","prat","rato"]}},"ita+ragusa":{"en":{"value":"Ragusa","trigram":["ragusa","rag","agu","gus","usa","ragu","agus","gusa","ragus","agusa"]}},"ita+ravenna":{"en":{"value":"Ravenna","trigram":["ravenna","rav","ave","ven","enn","nna","rave","aven","venn","enna","raven","avenn","venna"]}},"ita+reggio_di_calabria":{"en":{"value":"Reggio di Calabria","trigram":["reggio","di","calabria","reg","egg","ggi","gio","io ","o d"," di","di ","i c"," ca","cal","ala","lab","abr","bri","ria","regg","eggi","ggio","gio ","io d","o di"," di ","di c","i ca"," cal","cala","alab","labr","abri","bria","reggi","eggio","ggio ","gio d","io di","o di "," di c","di ca","i cal"," cala","calab","alabr","labri","abria"]}},"ita+reggio_emilia":{"en":{"value":"Reggio Emilia","trigram":["reggio","emilia","reg","egg","ggi","gio","io ","o e"," em","emi","mil","ili","lia","regg","eggi","ggio","gio ","io e","o em"," emi","emil","mili","ilia","reggi","eggio","ggio ","gio e","io em","o emi"," emil","emili","milia"]}},"ita+rimini":{"en":{"value":"Rimini","trigram":["rimini","rim","imi","min","ini","rimi","imin","mini","rimin","imini"]}},"ita+rome":{"en":{"value":"Rome","trigram":["rome","rom","ome"]}},"ita+salerno":{"en":{"value":"Salerno","trigram":["salerno","sal","ale","ler","ern","rno","sale","aler","lern","erno","saler","alern","lerno"]}},"ita+san_dorligo_della_valle":{"en":{"value":"San Dorligo della Valle","trigram":["san","dorligo","della","valle","an ","n d"," do","dor","orl","rli","lig","igo","go ","o d"," de","del","ell","lla","la ","a v"," va","val","all","lle","san ","an d","n do"," dor","dorl","orli","rlig","ligo","igo ","go d","o de"," del","dell","ella","lla ","la v","a va"," val","vall","alle","san d","an do","n dor"," dorl","dorli","orlig","rligo","ligo ","igo d","go de","o del"," dell","ella ","lla v","la va","a val"," vall"]}},"ita+san_vito_dei_normanni":{"en":{"value":"San Vito dei Normanni","trigram":["san","vito","dei","normanni","an ","n v"," vi","vit","ito","to ","o d"," de","ei ","i n"," no","nor","orm","rma","man","ann","nni","san ","an v","n vi"," vit","ito ","to d","o de"," dei","dei ","ei n","i no"," nor","norm","orma","rman","mann","anni","san v","an vi","n vit"," vito","vito ","ito d","to de","o dei"," dei ","dei n","ei no","i nor"," norm","norma","orman","rmann","manni"]}},"ita+sassari":{"en":{"value":"Sassari","trigram":["sassari","sas","ass","ssa","sar","ari","sass","assa","ssar","sari","sassa","assar","ssari"]}},"ita+savona":{"en":{"value":"Savona","trigram":["savona","sav","avo","von","ona","savo","avon","vona","savon","avona"]}},"ita+siena":{"en":{"value":"Siena","trigram":["siena","sie","ien","ena","sien","iena"]}},"ita+siracusa":{"en":{"value":"Siracusa","trigram":["siracusa","sir","ira","rac","acu","cus","usa","sira","irac","racu","acus","cusa","sirac","iracu","racus","acusa"]}},"ita+strongoli":{"en":{"value":"Strongoli","trigram":["strongoli","str","tro","ron","ong","ngo","gol","oli","stro","tron","rong","ongo","ngol","goli","stron","trong","rongo","ongol","ngoli"]}},"ita+taranto":{"en":{"value":"Taranto","trigram":["taranto","tar","ara","ran","ant","nto","tara","aran","rant","anto","taran","arant","ranto"]}},"ita+terni":{"en":{"value":"Terni","trigram":["terni","ter","ern","rni","tern","erni"]}},"ita+trento":{"en":{"value":"Trento","trigram":["trento","tre","ren","ent","nto","tren","rent","ento","trent","rento"]}},"ita+treviso":{"en":{"value":"Treviso","trigram":["treviso","tre","rev","evi","vis","iso","trev","revi","evis","viso","trevi","revis","eviso"]}},"ita+trieste":{"en":{"value":"Trieste","trigram":["trieste","tri","rie","ies","est","ste","trie","ries","iest","este","tries","riest","ieste"]}},"ita+turin":{"en":{"value":"Turin","trigram":["turin","tur","uri","rin","turi","urin"]}},"ita+udine":{"en":{"value":"Udine","trigram":["udine","udi","din","ine","udin","dine"]}},"ita+urbino":{"en":{"value":"Urbino","trigram":["urbino","urb","rbi","bin","ino","urbi","rbin","bino","urbin","rbino"]}},"ita+venice":{"en":{"value":"Venice","trigram":["venice","ven","eni","nic","ice","veni","enic","nice","venic","enice"]}},"ita+varese":{"en":{"value":"Varese","trigram":["varese","var","are","res","ese","vare","ares","rese","vares","arese"]}},"ita+ventimiglia":{"en":{"value":"Ventimiglia","trigram":["ventimiglia","ven","ent","nti","tim","imi","mig","igl","gli","lia","vent","enti","ntim","timi","imig","migl","igli","glia","venti","entim","ntimi","timig","imigl","migli","iglia"]}},"ita+vibo_valentia":{"en":{"value":"Vibo Valentia","trigram":["vibo","valentia","vib","ibo","bo ","o v"," va","val","ale","len","ent","nti","tia","ibo ","bo v","o va"," val","vale","alen","lent","enti","ntia","vibo ","ibo v","bo va","o val"," vale","valen","alent","lenti","entia"]}},"ita+vicenza":{"en":{"value":"Vicenza","trigram":["vicenza","vic","ice","cen","enz","nza","vice","icen","cenz","enza","vicen","icenz","cenza"]}},"ita+verona":{"en":{"value":"Verona","trigram":["verona","ver","ero","ron","ona","vero","eron","rona","veron","erona"]}}}