{"tun+ariana":{"en":{"value":"Ariana","trigram":["ariana","ari","ria","ian","ana","aria","rian","iana","arian","riana"]}},"tun+beja":{"en":{"value":"Beja","trigram":["beja","bej","eja"]}},"tun+ben_gardane":{"en":{"value":"Ben Gardane","trigram":["ben","gardane","en ","n g"," ga","gar","ard","rda","dan","ane","ben ","en g","n ga"," gar","gard","arda","rdan","dane","ben g","en ga","n gar"," gard","garda","ardan","rdane"]}},"tun+dehiba":{"en":{"value":"Dehiba","trigram":["dehiba","deh","ehi","hib","iba","dehi","ehib","hiba","dehib","ehiba"]}},"tun+bizerte":{"en":{"value":"Bizerte","trigram":["bizerte","biz","ize","zer","ert","rte","bize","izer","zert","erte","bizer","izert","zerte"]}},"tun+jendouba":{"en":{"value":"Jendouba","trigram":["jendouba","jen","end","ndo","dou","oub","uba","jend","endo","ndou","doub","ouba","jendo","endou","ndoub","douba"]}},"tun+ben_arous":{"en":{"value":"Ben Arous","trigram":["ben","arous","en ","n a"," ar","aro","rou","ous","ben ","en a","n ar"," aro","arou","rous","ben a","en ar","n aro"," arou"]}},"tun+gafsa":{"en":{"value":"Gafsa","trigram":["gafsa","gaf","afs","fsa","gafs","afsa"]}},"tun+kebili":{"en":{"value":"Kebili","trigram":["kebili","keb","ebi","bil","ili","kebi","ebil","bili","kebil","ebili"]}},"tun+gabes":{"en":{"value":"Gabes","trigram":["gabes","gab","abe","bes","gabe","abes"]}},"tun+kasserine":{"en":{"value":"Kasserine","trigram":["kasserine","kas","ass","sse","ser","eri","rin","ine","kass","asse","sser","seri","erin","rine","kasse","asser","sseri","serin","erine"]}},"tun+el_kef":{"en":{"value":"El Kef","trigram":["el","kef","el ","l k"," ke","el k","l ke"," kef","el ke","l kef"]}},"tun+mahdia":{"en":{"value":"Mahdia","trigram":["mahdia","mah","ahd","hdi","dia","mahd","ahdi","hdia","mahdi","ahdia"]}},"tun+kairouan":{"en":{"value":"Kairouan","trigram":["kairouan","kai","air","iro","rou","oua","uan","kair","airo","irou","roua","ouan","kairo","airou","iroua","rouan"]}},"tun+manouba":{"en":{"value":"Manouba","trigram":["manouba","man","ano","nou","oub","uba","mano","anou","noub","ouba","manou","anoub","nouba"]}},"tun+medenine":{"en":{"value":"Medenine","trigram":["medenine","med","ede","den","eni","nin","ine","mede","eden","deni","enin","nine","meden","edeni","denin","enine"]}},"tun+nabeul":{"en":{"value":"Nabeul","trigram":["nabeul","nab","abe","beu","eul","nabe","abeu","beul","nabeu","abeul"]}},"tun+monastir":{"en":{"value":"Monastir","trigram":["monastir","mon","ona","nas","ast","sti","tir","mona","onas","nast","asti","stir","monas","onast","nasti","astir"]}},"tun+sfax":{"en":{"value":"Sfax","trigram":["sfax","sfa","fax"]}},"tun+sidi_bouzid":{"en":{"value":"Sidi Bouzid","trigram":["sidi","bouzid","sid","idi","di ","i b"," bo","bou","ouz","uzi","zid","idi ","di b","i bo"," bou","bouz","ouzi","uzid","sidi ","idi b","di bo","i bou"," bouz","bouzi","ouzid"]}},"tun+siliana":{"en":{"value":"Siliana","trigram":["siliana","sil","ili","lia","ian","ana","sili","ilia","lian","iana","silia","ilian","liana"]}},"tun+tataouine":{"en":{"value":"Tataouine","trigram":["tataouine","tat","ata","tao","aou","oui","uin","ine","tata","atao","taou","aoui","ouin","uine","tatao","ataou","taoui","aouin","ouine"]}},"tun+tozeur":{"en":{"value":"Tozeur","trigram":["tozeur","toz","oze","zeu","eur","toze","ozeu","zeur","tozeu","ozeur"]}},"tun+sousse":{"en":{"value":"Sousse","trigram":["sousse","sou","ous","uss","sse","sous","ouss","usse","souss","ousse"]}},"tun+tunis":{"en":{"value":"Tunis","trigram":["tunis","tun","uni","nis","tuni","unis"]}},"tun+zaouiet_sousse":{"en":{"value":"Zaouiet Sousse","trigram":["zaouiet","sousse","zao","aou","oui","uie","iet","et ","t s"," so","sou","ous","uss","sse","zaou","aoui","ouie","uiet","iet ","et s","t so"," sou","sous","ouss","usse","zaoui","aouie","ouiet","uiet ","iet s","et so","t sou"," sous","souss","ousse"]}},"tun+zaghouan":{"en":{"value":"Zaghouan","trigram":["zaghouan","zag","agh","gho","hou","oua","uan","zagh","agho","ghou","houa","ouan","zagho","aghou","ghoua","houan"]}},"tun+zarzis":{"en":{"value":"Zarzis","trigram":["zarzis","zar","arz","rzi","zis","zarz","arzi","rzis","zarzi","arzis"]}}}