{"us_nm+alamogordo":{"en":{"value":"Alamogordo","trigram":["alamogordo","ala","lam","amo","mog","ogo","gor","ord","rdo","alam","lamo","amog","mogo","ogor","gord","ordo","alamo","lamog","amogo","mogor","ogord","gordo"]}},"us_nm+albuquerque":{"en":{"value":"Albuquerque","trigram":["albuquerque","alb","lbu","buq","uqu","que","uer","erq","rqu","albu","lbuq","buqu","uque","quer","uerq","erqu","rque","albuq","lbuqu","buque","uquer","querq","uerqu","erque"]}},"us_nm+anthony":{"en":{"value":"Anthony","trigram":["anthony","ant","nth","tho","hon","ony","anth","ntho","thon","hony","antho","nthon","thony"]}},"us_nm+artesia":{"en":{"value":"Artesia","trigram":["artesia","art","rte","tes","esi","sia","arte","rtes","tesi","esia","artes","rtesi","tesia"]}},"us_nm+aztec":{"en":{"value":"Aztec","trigram":["aztec","azt","zte","tec","azte","ztec"]}},"us_nm+belen":{"en":{"value":"Belen","trigram":["belen","bel","ele","len","bele","elen"]}},"us_nm+bernalillo":{"en":{"value":"Bernalillo","trigram":["bernalillo","ber","ern","rna","nal","ali","lil","ill","llo","bern","erna","rnal","nali","alil","lill","illo","berna","ernal","rnali","nalil","alill","lillo"]}},"us_nm+bloomfield":{"en":{"value":"Bloomfield","trigram":["bloomfield","blo","loo","oom","omf","mfi","fie","iel","eld","bloo","loom","oomf","omfi","mfie","fiel","ield","bloom","loomf","oomfi","omfie","mfiel","field"]}},"us_nm+carlsbad":{"en":{"value":"Carlsbad","trigram":["carlsbad","car","arl","rls","lsb","sba","bad","carl","arls","rlsb","lsba","sbad","carls","arlsb","rlsba","lsbad"]}},"us_nm+chaparral":{"en":{"value":"Chaparral","trigram":["chaparral","cha","hap","apa","par","arr","rra","ral","chap","hapa","apar","parr","arra","rral","chapa","hapar","aparr","parra","arral"]}},"us_nm+clovis":{"en":{"value":"Clovis","trigram":["clovis","clo","lov","ovi","vis","clov","lovi","ovis","clovi","lovis"]}},"us_nm+corrales":{"en":{"value":"Corrales","trigram":["corrales","cor","orr","rra","ral","ale","les","corr","orra","rral","rale","ales","corra","orral","rrale","rales"]}},"us_nm+deming":{"en":{"value":"Deming","trigram":["deming","dem","emi","min","ing","demi","emin","ming","demin","eming"]}},"us_nm+edgewood":{"en":{"value":"Edgewood","trigram":["edgewood","edg","dge","gew","ewo","woo","ood","edge","dgew","gewo","ewoo","wood","edgew","dgewo","gewoo","ewood"]}},"us_nm+eldorado_at_santa_fe":{"en":{"value":"Eldorado at santa fe","trigram":["eldorado","at","santa","fe","eld","ldo","dor","ora","rad","ado","do ","o a"," at","at ","t s"," sa","san","ant","nta","ta ","a f"," fe","eldo","ldor","dora","orad","rado","ado ","do a","o at"," at ","at s","t sa"," san","sant","anta","nta ","ta f","a fe","eldor","ldora","dorad","orado","rado ","ado a","do at","o at "," at s","at sa","t san"," sant","anta ","nta f","ta fe"]}},"us_nm+espanola":{"en":{"value":"Espanola","trigram":["espanola","esp","spa","pan","ano","nol","ola","espa","span","pano","anol","nola","espan","spano","panol","anola"]}},"us_nm+farmington":{"en":{"value":"Farmington","trigram":["farmington","far","arm","rmi","min","ing","ngt","gto","ton","farm","armi","rmin","ming","ingt","ngto","gton","farmi","armin","rming","mingt","ingto","ngton"]}},"us_nm+gallup":{"en":{"value":"Gallup","trigram":["gallup","gal","all","llu","lup","gall","allu","llup","gallu","allup"]}},"us_nm+grants":{"en":{"value":"Grants","trigram":["grants","gra","ran","ant","nts","gran","rant","ants","grant","rants"]}},"us_nm+hobbs":{"en":{"value":"Hobbs","trigram":["hobbs","hob","obb","bbs","hobb","obbs"]}},"us_nm+las_cruces":{"en":{"value":"Las cruces","trigram":["las","cruces","as ","s c"," cr","cru","ruc","uce","ces","las ","as c","s cr"," cru","cruc","ruce","uces","las c","as cr","s cru"," cruc","cruce","ruces"]}},"us_nm+las_vegas":{"en":{"value":"Las vegas","trigram":["las","vegas","as ","s v"," ve","veg","ega","gas","las ","as v","s ve"," veg","vega","egas","las v","as ve","s veg"," vega"]}},"us_nm+lee_acres":{"en":{"value":"Lee acres","trigram":["lee","acres","ee ","e a"," ac","acr","cre","res","lee ","ee a","e ac"," acr","acre","cres","lee a","ee ac","e acr"," acre"]}},"us_nm+los_alamos":{"en":{"value":"Los alamos","trigram":["los","alamos","os ","s a"," al","ala","lam","amo","mos","los ","os a","s al"," ala","alam","lamo","amos","los a","os al","s ala"," alam","alamo","lamos"]}},"us_nm+los_chaves":{"en":{"value":"Los chaves","trigram":["los","chaves","os ","s c"," ch","cha","hav","ave","ves","los ","os c","s ch"," cha","chav","have","aves","los c","os ch","s cha"," chav","chave","haves"]}},"us_nm+los_lunas":{"en":{"value":"Los lunas","trigram":["los","lunas","os ","s l"," lu","lun","una","nas","los ","os l","s lu"," lun","luna","unas","los l","os lu","s lun"," luna"]}},"us_nm+los_ranchos_de_albuquerque":{"en":{"value":"Los ranchos de albuquerque","trigram":["los","ranchos","de","albuquerque","os ","s r"," ra","ran","anc","nch","cho","hos","s d"," de","de ","e a"," al","alb","lbu","buq","uqu","que","uer","erq","rqu","los ","os r","s ra"," ran","ranc","anch","ncho","chos","hos ","os d","s de"," de ","de a","e al"," alb","albu","lbuq","buqu","uque","quer","uerq","erqu","rque","los r","os ra","s ran"," ranc","ranch","ancho","nchos","chos ","hos d","os de","s de "," de a","de al","e alb"," albu","albuq","lbuqu","buque","uquer","querq","uerqu","erque"]}},"us_nm+lovington":{"en":{"value":"Lovington","trigram":["lovington","lov","ovi","vin","ing","ngt","gto","ton","lovi","ovin","ving","ingt","ngto","gton","lovin","oving","vingt","ingto","ngton"]}},"us_nm+north_hobbs":{"en":{"value":"North hobbs","trigram":["north","hobbs","nor","ort","rth","th ","h h"," ho","hob","obb","bbs","nort","orth","rth ","th h","h ho"," hob","hobb","obbs","orth ","rth h","th ho","h hob"," hobb"]}},"us_nm+north_valley":{"en":{"value":"North valley","trigram":["north","valley","nor","ort","rth","th ","h v"," va","val","all","lle","ley","nort","orth","rth ","th v","h va"," val","vall","alle","lley","orth ","rth v","th va","h val"," vall","valle","alley"]}},"us_nm+paradise_hills":{"en":{"value":"Paradise hills","trigram":["paradise","hills","par","ara","rad","adi","dis","ise","se ","e h"," hi","hil","ill","lls","para","arad","radi","adis","dise","ise ","se h","e hi"," hil","hill","ills","parad","aradi","radis","adise","dise ","ise h","se hi","e hil"," hill"]}},"us_nm+portales":{"en":{"value":"Portales","trigram":["portales","por","ort","rta","tal","ale","les","port","orta","rtal","tale","ales","porta","ortal","rtale","tales"]}},"us_nm+raton":{"en":{"value":"Raton","trigram":["raton","rat","ato","ton","rato","aton"]}},"us_nm+rio_rancho":{"en":{"value":"Rio rancho","trigram":["rio","rancho","io ","o r"," ra","ran","anc","nch","cho","rio ","io r","o ra"," ran","ranc","anch","ncho","rio r","io ra","o ran"," ranc","ranch","ancho"]}},"us_nm+roswell":{"en":{"value":"Roswell","trigram":["roswell","ros","osw","swe","wel","ell","rosw","oswe","swel","well","roswe","oswel","swell"]}},"us_nm+ruidoso":{"en":{"value":"Ruidoso","trigram":["ruidoso","rui","uid","ido","dos","oso","ruid","uido","idos","doso","ruido","uidos","idoso"]}},"us_nm+santa_fe":{"en":{"value":"Santa fe","trigram":["santa","fe","san","ant","nta","ta ","a f"," fe","sant","anta","nta ","ta f","a fe","anta ","nta f","ta fe"]}},"us_nm+santa_teresa":{"en":{"value":"Santa teresa","trigram":["santa","teresa","san","ant","nta","ta ","a t"," te","ter","ere","res","esa","sant","anta","nta ","ta t","a te"," ter","tere","eres","resa","anta ","nta t","ta te","a ter"," tere","teres","eresa"]}},"us_nm+shiprock":{"en":{"value":"Shiprock","trigram":["shiprock","shi","hip","ipr","pro","roc","ock","ship","hipr","ipro","proc","rock","shipr","hipro","iproc","prock"]}},"us_nm+silver_city":{"en":{"value":"Silver city","trigram":["silver","city","sil","ilv","lve","ver","er ","r c"," ci","cit","ity","silv","ilve","lver","ver ","er c","r ci"," cit","silve","ilver","lver ","ver c","er ci","r cit"," city"]}},"us_nm+socorro":{"en":{"value":"Socorro","trigram":["socorro","soc","oco","cor","orr","rro","soco","ocor","corr","orro","socor","ocorr","corro"]}},"us_nm+south_valley":{"en":{"value":"South valley","trigram":["south","valley","sou","out","uth","th ","h v"," va","val","all","lle","ley","sout","outh","uth ","th v","h va"," val","vall","alle","lley","outh ","uth v","th va","h val"," vall","valle","alley"]}},"us_nm+sunland_park":{"en":{"value":"Sunland park","trigram":["sunland","park","sun","unl","nla","lan","and","nd ","d p"," pa","par","ark","sunl","unla","nlan","land","and ","nd p","d pa"," par","sunla","unlan","nland","land ","and p","nd pa","d par"," park"]}},"us_nm+taos":{"en":{"value":"Taos","trigram":["taos","tao","aos"]}},"us_nm+truth_or_consequences":{"en":{"value":"Truth or consequences","trigram":["truth","or","consequences","tru","rut","uth","th ","h o"," or","or ","r c"," co","con","ons","nse","seq","equ","que","uen","enc","nce","ces","trut","ruth","uth ","th o","h or"," or ","or c","r co"," con","cons","onse","nseq","sequ","eque","quen","uenc","ence","nces","ruth ","uth o","th or","h or "," or c","or co","r con"," cons","conse","onseq","nsequ","seque","equen","quenc","uence","ences"]}},"us_nm+white_rock":{"en":{"value":"White rock","trigram":["white","rock","whi","hit","ite","te ","e r"," ro","roc","ock","whit","hite","ite ","te r","e ro"," roc","hite ","ite r","te ro","e roc"," rock"]}},"us_nm+zuni_pueblo":{"en":{"value":"Zuni pueblo","trigram":["zuni","pueblo","zun","uni","ni ","i p"," pu","pue","ueb","ebl","blo","uni ","ni p","i pu"," pue","pueb","uebl","eblo","zuni ","uni p","ni pu","i pue"," pueb","puebl","ueblo"]}}}