{"zmb+chililabombwe":{"en":{"value":"Chililabombwe","trigram":["chililabombwe","chi","hil","ili","lil","ila","lab","abo","bom","omb","mbw","bwe","chil","hili","ilil","lila","ilab","labo","abom","bomb","ombw","mbwe","chili","hilil","ilila","lilab","ilabo","labom","abomb","bombw","ombwe"]}},"zmb+chingola":{"en":{"value":"Chingola","trigram":["chingola","chi","hin","ing","ngo","gol","ola","chin","hing","ingo","ngol","gola","ching","hingo","ingol","ngola"]}},"zmb+chipata":{"en":{"value":"Chipata","trigram":["chipata","chi","hip","ipa","pat","ata","chip","hipa","ipat","pata","chipa","hipat","ipata"]}},"zmb+kabwe":{"en":{"value":"Kabwe","trigram":["kabwe","kab","abw","bwe","kabw","abwe"]}},"zmb+chinsali":{"en":{"value":"Chinsali","trigram":["chinsali","chi","hin","ins","nsa","sal","ali","chin","hins","insa","nsal","sali","chins","hinsa","insal","nsali"]}},"zmb+kalabo":{"en":{"value":"Kalabo","trigram":["kalabo","kal","ala","lab","abo","kala","alab","labo","kalab","alabo"]}},"zmb+kapiri_mposhi":{"en":{"value":"Kapiri Mposhi","trigram":["kapiri","mposhi","kap","api","pir","iri","ri ","i m"," mp","mpo","pos","osh","shi","kapi","apir","piri","iri ","ri m","i mp"," mpo","mpos","posh","oshi","kapir","apiri","piri ","iri m","ri mp","i mpo"," mpos","mposh","poshi"]}},"zmb+kaoma":{"en":{"value":"Kaoma","trigram":["kaoma","kao","aom","oma","kaom","aoma"]}},"zmb+choma":{"en":{"value":"Choma","trigram":["choma","cho","hom","oma","chom","homa"]}},"zmb+kafue":{"en":{"value":"Kafue","trigram":["kafue","kaf","afu","fue","kafu","afue"]}},"zmb+kasama":{"en":{"value":"Kasama","trigram":["kasama","kas","asa","sam","ama","kasa","asam","sama","kasam","asama"]}},"zmb+kasempa":{"en":{"value":"Kasempa","trigram":["kasempa","kas","ase","sem","emp","mpa","kase","asem","semp","empa","kasem","asemp","sempa"]}},"zmb+kawambwa":{"en":{"value":"Kawambwa","trigram":["kawambwa","kaw","awa","wam","amb","mbw","bwa","kawa","awam","wamb","ambw","mbwa","kawam","awamb","wambw","ambwa"]}},"zmb+kitwe":{"en":{"value":"Kitwe","trigram":["kitwe","kit","itw","twe","kitw","itwe"]}},"zmb+livingstone":{"en":{"value":"Livingstone","trigram":["livingstone","liv","ivi","vin","ing","ngs","gst","sto","ton","one","livi","ivin","ving","ings","ngst","gsto","ston","tone","livin","iving","vings","ingst","ngsto","gston","stone"]}},"zmb+luanshya":{"en":{"value":"Luanshya","trigram":["luanshya","lua","uan","ans","nsh","shy","hya","luan","uans","ansh","nshy","shya","luans","uansh","anshy","nshya"]}},"zmb+kashikishi":{"en":{"value":"Kashikishi","trigram":["kashikishi","kas","ash","shi","hik","iki","kis","ish","kash","ashi","shik","hiki","ikis","kish","ishi","kashi","ashik","shiki","hikis","ikish","kishi"]}},"zmb+lundazi":{"en":{"value":"Lundazi","trigram":["lundazi","lun","und","nda","daz","azi","lund","unda","ndaz","dazi","lunda","undaz","ndazi"]}},"zmb+lukulu":{"en":{"value":"Lukulu","trigram":["lukulu","luk","uku","kul","ulu","luku","ukul","kulu","lukul","ukulu"]}},"zmb+lusaka":{"en":{"value":"Lusaka","trigram":["lusaka","lus","usa","sak","aka","lusa","usak","saka","lusak","usaka"]}},"zmb+mansa":{"en":{"value":"Mansa","trigram":["mansa","man","ans","nsa","mans","ansa"]}},"zmb+mazabuka":{"en":{"value":"Mazabuka","trigram":["mazabuka","maz","aza","zab","abu","buk","uka","maza","azab","zabu","abuk","buka","mazab","azabu","zabuk","abuka"]}},"zmb+mbala":{"en":{"value":"Mbala","trigram":["mbala","mba","bal","ala","mbal","bala"]}},"zmb+mongu":{"en":{"value":"Mongu","trigram":["mongu","mon","ong","ngu","mong","ongu"]}},"zmb+mpika":{"en":{"value":"Mpika","trigram":["mpika","mpi","pik","ika","mpik","pika"]}},"zmb+mufulira":{"en":{"value":"Mufulira","trigram":["mufulira","muf","ufu","ful","uli","lir","ira","mufu","uful","fuli","ulir","lira","muful","ufuli","fulir","ulira"]}},"zmb+mumbwa":{"en":{"value":"Mumbwa","trigram":["mumbwa","mum","umb","mbw","bwa","mumb","umbw","mbwa","mumbw","umbwa"]}},"zmb+mwinilunga":{"en":{"value":"Mwinilunga","trigram":["mwinilunga","mwi","win","ini","nil","ilu","lun","ung","nga","mwin","wini","inil","nilu","ilun","lung","unga","mwini","winil","inilu","nilun","ilung","lunga"]}},"zmb+nchelenge":{"en":{"value":"Nchelenge","trigram":["nchelenge","nch","che","hel","ele","len","eng","nge","nche","chel","hele","elen","leng","enge","nchel","chele","helen","eleng","lenge"]}},"zmb+ndola":{"en":{"value":"Ndola","trigram":["ndola","ndo","dol","ola","ndol","dola"]}},"zmb+nyimba":{"en":{"value":"Nyimba","trigram":["nyimba","nyi","yim","imb","mba","nyim","yimb","imba","nyimb","yimba"]}},"zmb+senanga":{"en":{"value":"Senanga","trigram":["senanga","sen","ena","nan","ang","nga","sena","enan","nang","anga","senan","enang","nanga"]}},"zmb+sesheke":{"en":{"value":"Sesheke","trigram":["sesheke","ses","esh","she","hek","eke","sesh","eshe","shek","heke","seshe","eshek","sheke"]}},"zmb+solwezi":{"en":{"value":"Solwezi","trigram":["solwezi","sol","olw","lwe","wez","ezi","solw","olwe","lwez","wezi","solwe","olwez","lwezi"]}},"zmb+zambezi":{"en":{"value":"Zambezi","trigram":["zambezi","zam","amb","mbe","bez","ezi","zamb","ambe","mbez","bezi","zambe","ambez","mbezi"]}}}